{
  "nodes": [
    {
      "id": "n1",
      "label": "累積IL\n-$3,094",
      "x": 1460,
      "y": 120,
      "width": 150,
      "height": 70,
      "color": "#e74c3c",
      "strokeColor": "#c0392b",
      "shape": "circle"
    },
    {
      "id": "n2",
      "label": "狭レンジ\n±3-5%",
      "x": 1180,
      "y": 80,
      "width": 120,
      "height": 50,
      "color": "#e67e22",
      "strokeColor": "#d35400",
      "shape": "roundRect"
    },
    {
      "id": "n3",
      "label": "即リバランス\nクールダウン無",
      "x": 1180,
      "y": 170,
      "width": 130,
      "height": 50,
      "color": "#e67e22",
      "strokeColor": "#d35400",
      "shape": "roundRect"
    },
    {
      "id": "n4",
      "label": "高ボラ無視\n固定レンジ",
      "x": 1740,
      "y": 80,
      "width": 120,
      "height": 50,
      "color": "#e67e22",
      "strokeColor": "#d35400",
      "shape": "roundRect"
    },
    {
      "id": "n5",
      "label": "USDC偏重\n83%超発生",
      "x": 1740,
      "y": 170,
      "width": 120,
      "height": 50,
      "color": "#e67e22",
      "strokeColor": "#d35400",
      "shape": "roundRect"
    },
    {
      "id": "n6",
      "label": "A: 固定%\n±5%固定",
      "x": 2220,
      "y": 100,
      "width": 140,
      "height": 55,
      "color": "#e74c3c",
      "strokeColor": "#c0392b",
      "shape": "roundRect"
    },
    {
      "id": "n7",
      "label": "B: ボラ連動\nATR×2σ",
      "x": 2460,
      "y": 100,
      "width": 140,
      "height": 55,
      "color": "#27ae60",
      "strokeColor": "#1e8449",
      "shape": "roundRect"
    },
    {
      "id": "n8",
      "label": "C: ボリンジャー\nBB(20,2)",
      "x": 2700,
      "y": 100,
      "width": 140,
      "height": 55,
      "color": "#3498db",
      "strokeColor": "#2980b9",
      "shape": "roundRect"
    },
    {
      "id": "n9",
      "label": "D: ハイブリッド\nボラ+トレンド",
      "x": 2940,
      "y": 100,
      "width": 140,
      "height": 55,
      "color": "#9b59b6",
      "strokeColor": "#8e44ad",
      "shape": "roundRect"
    },
    {
      "id": "n10",
      "label": "低ボラ",
      "x": 3260,
      "y": 90,
      "width": 100,
      "height": 40,
      "color": "#27ae60",
      "strokeColor": "#1e8449",
      "shape": "roundRect"
    },
    {
      "id": "n11",
      "label": "通常",
      "x": 3440,
      "y": 90,
      "width": 100,
      "height": 40,
      "color": "#3498db",
      "strokeColor": "#2980b9",
      "shape": "roundRect"
    },
    {
      "id": "n12",
      "label": "高ボラ",
      "x": 3620,
      "y": 90,
      "width": 100,
      "height": 40,
      "color": "#f39c12",
      "strokeColor": "#e67e22",
      "shape": "roundRect"
    },
    {
      "id": "n13",
      "label": "急変",
      "x": 3800,
      "y": 90,
      "width": 100,
      "height": 40,
      "color": "#e74c3c",
      "strokeColor": "#c0392b",
      "shape": "roundRect"
    },
    {
      "id": "n14",
      "label": "30秒\nチェック",
      "x": 4300,
      "y": 100,
      "width": 100,
      "height": 50,
      "color": "#3498db",
      "strokeColor": "#2980b9",
      "shape": "roundRect"
    },
    {
      "id": "n15",
      "label": "価格位置\n判定",
      "x": 4460,
      "y": 100,
      "width": 100,
      "height": 50,
      "color": "#f39c12",
      "strokeColor": "#e67e22",
      "shape": "diamond"
    },
    {
      "id": "n16",
      "label": "範囲内\n→待機",
      "x": 4620,
      "y": 70,
      "width": 100,
      "height": 40,
      "color": "#27ae60",
      "strokeColor": "#1e8449",
      "shape": "roundRect"
    },
    {
      "id": "n17",
      "label": "境界付近\n→通知",
      "x": 4620,
      "y": 130,
      "width": 100,
      "height": 40,
      "color": "#f39c12",
      "strokeColor": "#e67e22",
      "shape": "roundRect"
    },
    {
      "id": "n18",
      "label": "範囲外\n→実行判定",
      "x": 4780,
      "y": 100,
      "width": 120,
      "height": 50,
      "color": "#e74c3c",
      "strokeColor": "#c0392b",
      "shape": "roundRect"
    },
    {
      "id": "n19",
      "label": "クールダウン\n確認(4h)",
      "x": 4300,
      "y": 220,
      "width": 115,
      "height": 45,
      "color": "#9b59b6",
      "strokeColor": "#8e44ad",
      "shape": "roundRect"
    },
    {
      "id": "n20",
      "label": "コスト計算\n>50%skip",
      "x": 4460,
      "y": 220,
      "width": 115,
      "height": 45,
      "color": "#9b59b6",
      "strokeColor": "#8e44ad",
      "shape": "roundRect"
    },
    {
      "id": "n21",
      "label": "オラクル\n価格確認",
      "x": 4620,
      "y": 220,
      "width": 115,
      "height": 45,
      "color": "#9b59b6",
      "strokeColor": "#8e44ad",
      "shape": "roundRect"
    },
    {
      "id": "n22",
      "label": "シミュ\nレーション",
      "x": 4780,
      "y": 220,
      "width": 115,
      "height": 45,
      "color": "#9b59b6",
      "strokeColor": "#8e44ad",
      "shape": "roundRect"
    },
    {
      "id": "n23",
      "label": "実行",
      "x": 4940,
      "y": 220,
      "width": 90,
      "height": 45,
      "color": "#27ae60",
      "strokeColor": "#1e8449",
      "shape": "roundRect"
    },
    {
      "id": "n24",
      "label": "L1\n監視のみ",
      "x": 5380,
      "y": 100,
      "width": 110,
      "height": 50,
      "color": "#3498db",
      "strokeColor": "#2980b9",
      "shape": "roundRect"
    },
    {
      "id": "n25",
      "label": "L2\n半自動",
      "x": 5580,
      "y": 100,
      "width": 110,
      "height": 50,
      "color": "#f39c12",
      "strokeColor": "#e67e22",
      "shape": "roundRect"
    },
    {
      "id": "n26",
      "label": "L3\n条件付き\n全自動",
      "x": 5780,
      "y": 100,
      "width": 130,
      "height": 55,
      "color": "#27ae60",
      "strokeColor": "#1e8449",
      "shape": "roundRect"
    },
    {
      "id": "n27",
      "label": "L4\n完全自動",
      "x": 6000,
      "y": 100,
      "width": 110,
      "height": 50,
      "color": "#9b59b6",
      "strokeColor": "#8e44ad",
      "shape": "roundRect"
    },
    {
      "id": "n28",
      "label": "C2: 最悪\n-$2,379",
      "x": 7540,
      "y": 90,
      "width": 140,
      "height": 55,
      "color": "#e74c3c",
      "strokeColor": "#c0392b",
      "shape": "circle"
    },
    {
      "id": "n29",
      "label": "C7: 最良\n+$32",
      "x": 7780,
      "y": 90,
      "width": 140,
      "height": 55,
      "color": "#27ae60",
      "strokeColor": "#1e8449",
      "shape": "circle"
    },
    {
      "id": "n30",
      "label": "→",
      "x": 7745,
      "y": 350,
      "width": 30,
      "height": 30,
      "color": "#f1c40f",
      "strokeColor": "#f39c12",
      "shape": "circle"
    },
    {
      "id": "n31",
      "label": "VPS\nHetzner\nCPX11",
      "x": 8560,
      "y": 100,
      "width": 110,
      "height": 60,
      "color": "#3498db",
      "strokeColor": "#2980b9",
      "shape": "rect"
    },
    {
      "id": "n32",
      "label": "Docker\nコンテナ",
      "x": 8730,
      "y": 100,
      "width": 110,
      "height": 60,
      "color": "#2c3e50",
      "strokeColor": "#1a252f",
      "shape": "rect"
    },
    {
      "id": "n33",
      "label": "リバランサー\nBot (TS)",
      "x": 8900,
      "y": 80,
      "width": 120,
      "height": 50,
      "color": "#27ae60",
      "strokeColor": "#1e8449",
      "shape": "roundRect"
    },
    {
      "id": "n34",
      "label": "モニター\n& アラート",
      "x": 8900,
      "y": 145,
      "width": 120,
      "height": 50,
      "color": "#f39c12",
      "strokeColor": "#e67e22",
      "shape": "roundRect"
    },
    {
      "id": "n35",
      "label": "SQLite\nDB",
      "x": 9070,
      "y": 100,
      "width": 100,
      "height": 60,
      "color": "#9b59b6",
      "strokeColor": "#8e44ad",
      "shape": "rect"
    },
    {
      "id": "n36",
      "label": "Helius\n$49/月",
      "x": 9230,
      "y": 70,
      "width": 110,
      "height": 40,
      "color": "#3498db",
      "strokeColor": "#2980b9",
      "shape": "roundRect"
    },
    {
      "id": "n37",
      "label": "Shinami\n無料",
      "x": 9230,
      "y": 125,
      "width": 110,
      "height": 40,
      "color": "#27ae60",
      "strokeColor": "#1e8449",
      "shape": "roundRect"
    },
    {
      "id": "n38",
      "label": "Public\nフォールバック",
      "x": 9230,
      "y": 180,
      "width": 110,
      "height": 40,
      "color": "#7f8c8d",
      "strokeColor": "#566573",
      "shape": "roundRect"
    },
    {
      "id": "n39",
      "label": "SOL/USDC\n60-65%\n$30-32.5K",
      "x": 9660,
      "y": 100,
      "width": 140,
      "height": 60,
      "color": "#3498db",
      "strokeColor": "#2980b9",
      "shape": "roundRect"
    },
    {
      "id": "n40",
      "label": "SUI/USDC\n15%\n$7.5K",
      "x": 9890,
      "y": 100,
      "width": 130,
      "height": 60,
      "color": "#9b59b6",
      "strokeColor": "#8e44ad",
      "shape": "roundRect"
    },
    {
      "id": "n41",
      "label": "SOL/mSOL\n10%\n$5K",
      "x": 10100,
      "y": 100,
      "width": 130,
      "height": 60,
      "color": "#27ae60",
      "strokeColor": "#1e8449",
      "shape": "roundRect"
    },
    {
      "id": "n42",
      "label": "USDC予備\n10-15%\n$5-7.5K",
      "x": 10310,
      "y": 100,
      "width": 130,
      "height": 60,
      "color": "#f39c12",
      "strokeColor": "#e67e22",
      "shape": "roundRect"
    },
    {
      "id": "n43",
      "label": "#1 D\nボラ連動",
      "x": 10700,
      "y": 90,
      "width": 120,
      "height": 50,
      "color": "#27ae60",
      "strokeColor": "#1e8449",
      "shape": "roundRect"
    },
    {
      "id": "n44",
      "label": "#2 B\n広レンジ",
      "x": 10880,
      "y": 90,
      "width": 120,
      "height": 50,
      "color": "#3498db",
      "strokeColor": "#2980b9",
      "shape": "roundRect"
    },
    {
      "id": "n45",
      "label": "#3 F\nトレンド",
      "x": 11060,
      "y": 90,
      "width": 120,
      "height": 50,
      "color": "#9b59b6",
      "strokeColor": "#8e44ad",
      "shape": "roundRect"
    },
    {
      "id": "n46",
      "label": "最下位 A\n狭レンジ(現状)",
      "x": 11300,
      "y": 90,
      "width": 150,
      "height": 50,
      "color": "#e74c3c",
      "strokeColor": "#c0392b",
      "shape": "roundRect"
    },
    {
      "id": "n47",
      "label": "即時\n(今週)",
      "x": 11740,
      "y": 90,
      "width": 100,
      "height": 45,
      "color": "#e74c3c",
      "strokeColor": "#c0392b",
      "shape": "roundRect"
    },
    {
      "id": "n48",
      "label": "1ヶ月",
      "x": 11940,
      "y": 90,
      "width": 100,
      "height": 45,
      "color": "#f39c12",
      "strokeColor": "#e67e22",
      "shape": "roundRect"
    },
    {
      "id": "n49",
      "label": "1-3ヶ月",
      "x": 12140,
      "y": 90,
      "width": 110,
      "height": 45,
      "color": "#3498db",
      "strokeColor": "#2980b9",
      "shape": "roundRect"
    },
    {
      "id": "n50",
      "label": "3-6ヶ月",
      "x": 12360,
      "y": 90,
      "width": 110,
      "height": 45,
      "color": "#27ae60",
      "strokeColor": "#1e8449",
      "shape": "roundRect"
    },
    {
      "id": "n51",
      "label": "保守的\n+3% APR",
      "x": 12840,
      "y": 80,
      "width": 130,
      "height": 50,
      "color": "#e74c3c",
      "strokeColor": "#c0392b",
      "shape": "roundRect"
    },
    {
      "id": "n52",
      "label": "基本\n+16% APR",
      "x": 13120,
      "y": 80,
      "width": 130,
      "height": 50,
      "color": "#3498db",
      "strokeColor": "#2980b9",
      "shape": "roundRect"
    },
    {
      "id": "n53",
      "label": "楽観的\n+28% APR",
      "x": 13400,
      "y": 80,
      "width": 130,
      "height": 50,
      "color": "#27ae60",
      "strokeColor": "#1e8449",
      "shape": "roundRect"
    }
  ],
  "edges": [
    {
      "id": "e1",
      "sourceId": "n2",
      "targetId": "n1",
      "label": "",
      "color": "#e74c3c",
      "strokeWidth": 2,
      "pathStyle": "curved",
      "direction": "forward"
    },
    {
      "id": "e2",
      "sourceId": "n3",
      "targetId": "n1",
      "label": "",
      "color": "#e74c3c",
      "strokeWidth": 2,
      "pathStyle": "curved",
      "direction": "forward"
    },
    {
      "id": "e3",
      "sourceId": "n4",
      "targetId": "n1",
      "label": "",
      "color": "#e74c3c",
      "strokeWidth": 2,
      "pathStyle": "curved",
      "direction": "forward"
    },
    {
      "id": "e4",
      "sourceId": "n5",
      "targetId": "n1",
      "label": "",
      "color": "#e74c3c",
      "strokeWidth": 2,
      "pathStyle": "curved",
      "direction": "forward"
    },
    {
      "id": "e5",
      "sourceId": "n10",
      "targetId": "n11",
      "label": "ボラ上昇",
      "color": "#7f8c8d",
      "strokeWidth": 2,
      "pathStyle": "straight",
      "direction": "forward"
    },
    {
      "id": "e6",
      "sourceId": "n11",
      "targetId": "n12",
      "label": "ボラ上昇",
      "color": "#f39c12",
      "strokeWidth": 2,
      "pathStyle": "straight",
      "direction": "forward"
    },
    {
      "id": "e7",
      "sourceId": "n12",
      "targetId": "n13",
      "label": "急騰/急落",
      "color": "#e74c3c",
      "strokeWidth": 2,
      "pathStyle": "straight",
      "direction": "forward"
    },
    {
      "id": "e8",
      "sourceId": "n14",
      "targetId": "n15",
      "label": "",
      "color": "#3498db",
      "strokeWidth": 2,
      "pathStyle": "straight",
      "direction": "forward"
    },
    {
      "id": "e9",
      "sourceId": "n15",
      "targetId": "n16",
      "label": "範囲内",
      "color": "#27ae60",
      "strokeWidth": 2,
      "pathStyle": "straight",
      "direction": "forward"
    },
    {
      "id": "e10",
      "sourceId": "n15",
      "targetId": "n17",
      "label": "境界",
      "color": "#f39c12",
      "strokeWidth": 2,
      "pathStyle": "straight",
      "direction": "forward"
    },
    {
      "id": "e11",
      "sourceId": "n15",
      "targetId": "n18",
      "label": "範囲外",
      "color": "#e74c3c",
      "strokeWidth": 2,
      "pathStyle": "straight",
      "direction": "forward"
    },
    {
      "id": "e12",
      "sourceId": "n18",
      "targetId": "n19",
      "label": "",
      "color": "#9b59b6",
      "strokeWidth": 2,
      "pathStyle": "curved",
      "direction": "forward"
    },
    {
      "id": "e13",
      "sourceId": "n19",
      "targetId": "n20",
      "label": "OK",
      "color": "#9b59b6",
      "strokeWidth": 2,
      "pathStyle": "straight",
      "direction": "forward"
    },
    {
      "id": "e14",
      "sourceId": "n20",
      "targetId": "n21",
      "label": "OK",
      "color": "#9b59b6",
      "strokeWidth": 2,
      "pathStyle": "straight",
      "direction": "forward"
    },
    {
      "id": "e15",
      "sourceId": "n21",
      "targetId": "n22",
      "label": "OK",
      "color": "#9b59b6",
      "strokeWidth": 2,
      "pathStyle": "straight",
      "direction": "forward"
    },
    {
      "id": "e16",
      "sourceId": "n22",
      "targetId": "n23",
      "label": "OK",
      "color": "#27ae60",
      "strokeWidth": 2,
      "pathStyle": "straight",
      "direction": "forward"
    },
    {
      "id": "e17",
      "sourceId": "n24",
      "targetId": "n25",
      "label": "Phase1",
      "color": "#7f8c8d",
      "strokeWidth": 2,
      "pathStyle": "straight",
      "direction": "forward"
    },
    {
      "id": "e18",
      "sourceId": "n25",
      "targetId": "n26",
      "label": "Phase2",
      "color": "#7f8c8d",
      "strokeWidth": 2,
      "pathStyle": "straight",
      "direction": "forward"
    },
    {
      "id": "e19",
      "sourceId": "n26",
      "targetId": "n27",
      "label": "Phase3",
      "color": "#7f8c8d",
      "strokeWidth": 2,
      "pathStyle": "straight",
      "direction": "forward"
    },
    {
      "id": "e20",
      "sourceId": "n31",
      "targetId": "n32",
      "label": "",
      "color": "#3498db",
      "strokeWidth": 2,
      "pathStyle": "straight",
      "direction": "forward"
    },
    {
      "id": "e21",
      "sourceId": "n32",
      "targetId": "n33",
      "label": "",
      "color": "#27ae60",
      "strokeWidth": 2,
      "pathStyle": "straight",
      "direction": "forward"
    },
    {
      "id": "e22",
      "sourceId": "n32",
      "targetId": "n34",
      "label": "",
      "color": "#f39c12",
      "strokeWidth": 2,
      "pathStyle": "straight",
      "direction": "forward"
    },
    {
      "id": "e23",
      "sourceId": "n33",
      "targetId": "n35",
      "label": "TX記録",
      "color": "#9b59b6",
      "strokeWidth": 2,
      "pathStyle": "straight",
      "direction": "forward"
    },
    {
      "id": "e24",
      "sourceId": "n34",
      "targetId": "n35",
      "label": "ログ",
      "color": "#9b59b6",
      "strokeWidth": 2,
      "pathStyle": "straight",
      "direction": "forward"
    },
    {
      "id": "e25",
      "sourceId": "n33",
      "targetId": "n36",
      "label": "プライマリ",
      "color": "#3498db",
      "strokeWidth": 2,
      "pathStyle": "curved",
      "direction": "forward"
    },
    {
      "id": "e26",
      "sourceId": "n33",
      "targetId": "n37",
      "label": "セカンダリ",
      "color": "#27ae60",
      "strokeWidth": 1,
      "pathStyle": "curved",
      "direction": "forward"
    },
    {
      "id": "e27",
      "sourceId": "n33",
      "targetId": "n38",
      "label": "フォールバック",
      "color": "#7f8c8d",
      "strokeWidth": 1,
      "pathStyle": "curved",
      "direction": "forward"
    },
    {
      "id": "e28",
      "sourceId": "n47",
      "targetId": "n48",
      "label": "",
      "color": "#7f8c8d",
      "strokeWidth": 3,
      "pathStyle": "straight",
      "direction": "forward"
    },
    {
      "id": "e29",
      "sourceId": "n48",
      "targetId": "n49",
      "label": "",
      "color": "#7f8c8d",
      "strokeWidth": 3,
      "pathStyle": "straight",
      "direction": "forward"
    },
    {
      "id": "e30",
      "sourceId": "n49",
      "targetId": "n50",
      "label": "",
      "color": "#7f8c8d",
      "strokeWidth": 3,
      "pathStyle": "straight",
      "direction": "forward"
    }
  ],
  "textboxes": [
    {
      "id": "t1",
      "text": "CLMM Auto-Range Rebalancer",
      "x": 80,
      "y": 30,
      "width": 800,
      "height": 60,
      "fontSize": 32,
      "textColor": "#ffffff",
      "bgColor": "#2c3e50",
      "strokeColor": "#2c3e50",
      "cornerRadius": 12,
      "textAlign": "center",
      "paddingX": 10,
      "paddingY": 8
    },
    {
      "id": "t2",
      "text": "10ラウンド議論 総合ビジュアルガイド",
      "x": 230,
      "y": 95,
      "width": 500,
      "height": 35,
      "fontSize": 18,
      "textColor": "#ecf0f1",
      "bgColor": "#34495e",
      "strokeColor": "#34495e",
      "cornerRadius": 8,
      "textAlign": "center",
      "paddingX": 10,
      "paddingY": 8
    },
    {
      "id": "t3",
      "text": "■ 問題\n\n累IL: -$3,094\nレンジ外れ率: 90%\n狭レンジ ±3-5%\n即リバランスで損失拡大",
      "x": 40,
      "y": 160,
      "width": 270,
      "height": 200,
      "fontSize": 14,
      "textColor": "#ffffff",
      "bgColor": "#c0392b",
      "strokeColor": "#e74c3c",
      "cornerRadius": 12,
      "textAlign": "left",
      "paddingX": 10,
      "paddingY": 8
    },
    {
      "id": "t4",
      "text": "■ 解決策\n\nボラ連動2σレンジ\n4h最低クールダウン\n3層ポジション構造\nL3条件付き全自動化",
      "x": 345,
      "y": 160,
      "width": 270,
      "height": 200,
      "fontSize": 14,
      "textColor": "#ffffff",
      "bgColor": "#2980b9",
      "strokeColor": "#3498db",
      "cornerRadius": 12,
      "textAlign": "left",
      "paddingX": 10,
      "paddingY": 8
    },
    {
      "id": "t5",
      "text": "■ 期待効果\n\n推奨APR: +3%～+28%\nレンジ内率: 70%→80%+\n年間IL: $3,000→$800\nネット収益改善",
      "x": 650,
      "y": 160,
      "width": 270,
      "height": 200,
      "fontSize": 14,
      "textColor": "#ffffff",
      "bgColor": "#27ae60",
      "strokeColor": "#2ecc71",
      "cornerRadius": 12,
      "textAlign": "left",
      "paddingX": 10,
      "paddingY": 8
    },
    {
      "id": "t6",
      "text": "対象: $50K CLMM運用 | プール: SOL/USDC, SUI/USDC, SOL/mSOL | 基盤: Orca Whirlpool + Cetus",
      "x": 80,
      "y": 390,
      "width": 800,
      "height": 40,
      "fontSize": 13,
      "textColor": "#7f8c8d",
      "bgColor": "#ecf0f1",
      "strokeColor": "#bdc3c7",
      "cornerRadius": 8,
      "textAlign": "center",
      "paddingX": 10,
      "paddingY": 8
    },
    {
      "id": "t7",
      "text": "R1-R10 分析完了",
      "x": 80,
      "y": 450,
      "width": 180,
      "height": 35,
      "fontSize": 12,
      "textColor": "#2c3e50",
      "bgColor": "#f1c40f",
      "strokeColor": "#f39c12",
      "cornerRadius": 6,
      "textAlign": "center",
      "paddingX": 10,
      "paddingY": 8
    },
    {
      "id": "t8",
      "text": "バックテスト検証済",
      "x": 280,
      "y": 450,
      "width": 180,
      "height": 35,
      "fontSize": 12,
      "textColor": "#2c3e50",
      "bgColor": "#f1c40f",
      "strokeColor": "#f39c12",
      "cornerRadius": 6,
      "textAlign": "center",
      "paddingX": 10,
      "paddingY": 8
    },
    {
      "id": "t9",
      "text": "実装ロードマップ策定",
      "x": 480,
      "y": 450,
      "width": 180,
      "height": 35,
      "fontSize": 12,
      "textColor": "#2c3e50",
      "bgColor": "#f1c40f",
      "strokeColor": "#f39c12",
      "cornerRadius": 6,
      "textAlign": "center",
      "paddingX": 10,
      "paddingY": 8
    },
    {
      "id": "t10",
      "text": "税務・規制対応済",
      "x": 680,
      "y": 450,
      "width": 180,
      "height": 35,
      "fontSize": 12,
      "textColor": "#2c3e50",
      "bgColor": "#f1c40f",
      "strokeColor": "#f39c12",
      "cornerRadius": 6,
      "textAlign": "center",
      "paddingX": 10,
      "paddingY": 8
    },
    {
      "id": "t11",
      "text": "現状の問題分析（R1 リスク + R5 IL定量）",
      "x": 1100,
      "y": 10,
      "width": 880,
      "height": 40,
      "fontSize": 24,
      "textColor": "#ffffff",
      "bgColor": "#c0392b",
      "strokeColor": "#e74c3c",
      "cornerRadius": 12,
      "textAlign": "center",
      "paddingX": 10,
      "paddingY": 8
    },
    {
      "id": "t12",
      "text": "サイクル別IL分析\n\nC1: -$148 (SOL +6.3%)\nC2: -$2,379 ← 最悪 (USDC 83%)\nC3: -$215 (SOL -4.1%)\nC4: -$87 (レンジ内維持)\nC5: -$62 (小幅変動)\nC6: -$156 (急落局面)\nC7: +$32 ← 唯一プラス\nC8: -$34 (短期保持)\nC9: -$28 (改善傾向)\nC10: -$17 (最小IL)",
      "x": 1100,
      "y": 270,
      "width": 300,
      "height": 240,
      "fontSize": 12,
      "textColor": "#2c3e50",
      "bgColor": "#fdf2e9",
      "strokeColor": "#e67e22",
      "cornerRadius": 10,
      "textAlign": "left",
      "paddingX": 10,
      "paddingY": 8
    },
    {
      "id": "t13",
      "text": "リスクマトリクス\n\n影響大×確率高:\n  ・ レンジ外れ (90%発生)\n  ・ IL爆発 (USDC偏重時)\n影響大×確率中:\n  ・ スマコン脆弱性\n  ・ 価格オラクル遅延\n影響中×確率高:\n  ・ 高ガスコスト\n  ・ スリッページ損失\n影響中×確率中:\n  ・ RPC障害\n  ・ 流動性枯渇",
      "x": 1430,
      "y": 270,
      "width": 280,
      "height": 240,
      "fontSize": 12,
      "textColor": "#2c3e50",
      "bgColor": "#fdedec",
      "strokeColor": "#e74c3c",
      "cornerRadius": 10,
      "textAlign": "left",
      "paddingX": 10,
      "paddingY": 8
    },
    {
      "id": "t14",
      "text": "核心的問題\n\nレンジ外れ率90%は\n根本的な戦略ミス。\n\n狭レンジ+即リバランス=\n「高い手数料を払って\n損失を確定する」\nサイクルに陥っている。\n\nC2の-$2,379は\n全損失の77%を占める。",
      "x": 1740,
      "y": 270,
      "width": 240,
      "height": 240,
      "fontSize": 13,
      "textColor": "#ffffff",
      "bgColor": "#8e44ad",
      "strokeColor": "#9b59b6",
      "cornerRadius": 10,
      "textAlign": "left",
      "paddingX": 10,
      "paddingY": 8
    },
    {
      "id": "t15",
      "text": "レンジ戦略比較（R2 LP戦略分析）",
      "x": 2160,
      "y": 10,
      "width": 880,
      "height": 40,
      "fontSize": 24,
      "textColor": "#ffffff",
      "bgColor": "#2980b9",
      "strokeColor": "#3498db",
      "cornerRadius": 12,
      "textAlign": "center",
      "paddingX": 10,
      "paddingY": 8
    },
    {
      "id": "t16",
      "text": "★ 推奨",
      "x": 2490,
      "y": 70,
      "width": 80,
      "height": 25,
      "fontSize": 12,
      "textColor": "#ffffff",
      "bgColor": "#27ae60",
      "strokeColor": "#27ae60",
      "cornerRadius": 6,
      "textAlign": "center",
      "paddingX": 10,
      "paddingY": 8
    },
    {
      "id": "t17",
      "text": "戦略比較表\n\n戦略       | レンジ幅  | 手数料倍率 | IL耐性 | 複雑度\n───────────────────────────────────────\nA: 固定%    | ±5%     | 4.2x     | ✗ 低   | ★☆☆\nB: ボラ連動  | ±8-20%  | 2.1x     | ◎ 高   | ★★☆\nC: ボリンジャー| ±10-18% | 2.5x     | ○ 中   | ★★☆\nD: ハイブリッド| ±8-25%  | 1.8x     | ◎ 高   | ★★★",
      "x": 2160,
      "y": 190,
      "width": 580,
      "height": 160,
      "fontSize": 12,
      "textColor": "#2c3e50",
      "bgColor": "#eaf2f8",
      "strokeColor": "#3498db",
      "cornerRadius": 10,
      "textAlign": "left",
      "paddingX": 10,
      "paddingY": 8
    },
    {
      "id": "t18",
      "text": "勝者: ボラ連動2σ\n\n理由:\n・ IL耐性が最も高い\n・ 市場状態に自動適応\n・ 実装がシンプル\n・ バックテストで#1\n\n手数料倍率は固定の\n半分だが、IL削減で\n総合リターン優位",
      "x": 2770,
      "y": 190,
      "width": 270,
      "height": 160,
      "fontSize": 13,
      "textColor": "#ffffff",
      "bgColor": "#27ae60",
      "strokeColor": "#2ecc71",
      "cornerRadius": 10,
      "textAlign": "left",
      "paddingX": 10,
      "paddingY": 8
    },
    {
      "id": "t19",
      "text": "核心公式: レンジ幅 = ATR(14) × 2.0σ × √保持日数\n例: ATR=3.2%, 保持3日 → 3.2% × 2.0 × √3 = ±11.1% レンジ",
      "x": 2160,
      "y": 380,
      "width": 880,
      "height": 55,
      "fontSize": 14,
      "textColor": "#2c3e50",
      "bgColor": "#fef9e7",
      "strokeColor": "#f1c40f",
      "cornerRadius": 10,
      "textAlign": "center",
      "paddingX": 10,
      "paddingY": 8
    },
    {
      "id": "t20",
      "text": "レンジ幅と収益のトレードオフ: 狭→手数料↑ IL↑ | 広→手数料↓ IL↓ | 最適=ボラの2σが理論的バランス点",
      "x": 2160,
      "y": 460,
      "width": 880,
      "height": 40,
      "fontSize": 12,
      "textColor": "#7f8c8d",
      "bgColor": "#f8f9fa",
      "strokeColor": "#dee2e6",
      "cornerRadius": 8,
      "textAlign": "center",
      "paddingX": 10,
      "paddingY": 8
    },
    {
      "id": "t21",
      "text": "ボラティリティ連動2σ戦略の詳細",
      "x": 3220,
      "y": 10,
      "width": 880,
      "height": 40,
      "fontSize": 24,
      "textColor": "#ffffff",
      "bgColor": "#8e44ad",
      "strokeColor": "#9b59b6",
      "cornerRadius": 12,
      "textAlign": "center",
      "paddingX": 10,
      "paddingY": 8
    },
    {
      "id": "t22",
      "text": "SOL/USDC レンジ設定\n\n低ボラ期:   ±5～8%\n通常期:     ±10～12%\n高ボラ期:   ±15～20%\n急変時:     ポジションクローズ\n\nATR(14)閾値:\n  低ボラ < 2.5%\n  通常  2.5-5.0%\n  高ボラ 5.0-8.0%\n  急変  > 8.0%",
      "x": 3220,
      "y": 155,
      "width": 280,
      "height": 210,
      "fontSize": 12,
      "textColor": "#2c3e50",
      "bgColor": "#eaf2f8",
      "strokeColor": "#3498db",
      "cornerRadius": 10,
      "textAlign": "left",
      "paddingX": 10,
      "paddingY": 8
    },
    {
      "id": "t23",
      "text": "SUI/USDC レンジ設定\n\n低ボラ期:   ±7～10%\n通常期:     ±14～18%\n高ボラ期:   ±20～25%\n急変時:     ポジションクローズ\n\nSUIはSOLより高ボラ\n→ 全レンジを1.4倍に拡大\nTVL低下リスクも考慮",
      "x": 3520,
      "y": 155,
      "width": 280,
      "height": 210,
      "fontSize": 12,
      "textColor": "#2c3e50",
      "bgColor": "#f5eef8",
      "strokeColor": "#9b59b6",
      "cornerRadius": 10,
      "textAlign": "left",
      "paddingX": 10,
      "paddingY": 8
    },
    {
      "id": "t24",
      "text": "トレンドバイアス\n\nEMA(7) > EMA(21)の場合:\n→ 上方60% : 下方40%\n\nEMA(7) < EMA(21)の場合:\n→ 上方40% : 下方60%\n\n中立時: 50:50対称",
      "x": 3820,
      "y": 155,
      "width": 280,
      "height": 130,
      "fontSize": 12,
      "textColor": "#2c3e50",
      "bgColor": "#fef9e7",
      "strokeColor": "#f1c40f",
      "cornerRadius": 10,
      "textAlign": "left",
      "paddingX": 10,
      "paddingY": 8
    },
    {
      "id": "t25",
      "text": "3層ポジション構造\n\nコア:   50% ±8%  (高集中・高手数料)\nミドル: 30% ±15% (バランス)\nワイド: 20% ±25% (IL保護・常時稼働)\n\n→ 常にワイド層がレンジ内を維持",
      "x": 3820,
      "y": 300,
      "width": 280,
      "height": 135,
      "fontSize": 12,
      "textColor": "#ffffff",
      "bgColor": "#2c3e50",
      "strokeColor": "#2c3e50",
      "cornerRadius": 10,
      "textAlign": "left",
      "paddingX": 10,
      "paddingY": 8
    },
    {
      "id": "t26",
      "text": "核心: 市場が穏やかな時は攻め（狭レンジ高手数料）、荒れた時は守り（広レンジIL抑制）を自動切替",
      "x": 3220,
      "y": 480,
      "width": 880,
      "height": 35,
      "fontSize": 13,
      "textColor": "#e74c3c",
      "bgColor": "#fdf2e9",
      "strokeColor": "#e67e22",
      "cornerRadius": 8,
      "textAlign": "center",
      "paddingX": 10,
      "paddingY": 8
    },
    {
      "id": "t27",
      "text": "リバランスロジック フローチャート",
      "x": 4280,
      "y": 10,
      "width": 880,
      "height": 40,
      "fontSize": 24,
      "textColor": "#ffffff",
      "bgColor": "#2980b9",
      "strokeColor": "#3498db",
      "cornerRadius": 12,
      "textAlign": "center",
      "paddingX": 10,
      "paddingY": 8
    },
    {
      "id": "t28",
      "text": "リバランスルール\n\n・ 最低クールダウン: 4時間\n・ 最大リバランス: 6回/日\n・ コスト閾値: 期待手数料の50%超→スキップ\n・ オラクル乖離: DEX vs Oracle >1%→停止\n・ スリッページ上限: 0.5%\n・ 緊急停止: 価格急変>10%/1h",
      "x": 4280,
      "y": 310,
      "width": 420,
      "height": 160,
      "fontSize": 13,
      "textColor": "#2c3e50",
      "bgColor": "#fdedec",
      "strokeColor": "#e74c3c",
      "cornerRadius": 10,
      "textAlign": "left",
      "paddingX": 10,
      "paddingY": 8
    },
    {
      "id": "t29",
      "text": "リバランスコスト内訳\n\n1. ポジション解除: ~0.01 SOL\n2. トークンスワップ: スリッページ 0.1-0.5%\n3. 新ポジション作成: ~0.01 SOL\n4. 優先手数料(Jito): 0.001 SOL\n\n合計: 約$1-5/回\n月4-8回で $4-40/月",
      "x": 4730,
      "y": 310,
      "width": 430,
      "height": 160,
      "fontSize": 13,
      "textColor": "#2c3e50",
      "bgColor": "#eaf2f8",
      "strokeColor": "#3498db",
      "cornerRadius": 10,
      "textAlign": "left",
      "paddingX": 10,
      "paddingY": 8
    },
    {
      "id": "t30",
      "text": "重要: 「リバランスしない」判断も戦略の一部。コスト>期待利益ならスキップが最善",
      "x": 4280,
      "y": 490,
      "width": 880,
      "height": 30,
      "fontSize": 12,
      "textColor": "#e74c3c",
      "bgColor": "#fef9e7",
      "strokeColor": "#f1c40f",
      "cornerRadius": 6,
      "textAlign": "center",
      "paddingX": 10,
      "paddingY": 8
    },
    {
      "id": "t31",
      "text": "自動化レベルと実装フェーズ",
      "x": 5340,
      "y": 10,
      "width": 880,
      "height": 40,
      "fontSize": 24,
      "textColor": "#ffffff",
      "bgColor": "#2c3e50",
      "strokeColor": "#34495e",
      "cornerRadius": 12,
      "textAlign": "center",
      "paddingX": 10,
      "paddingY": 8
    },
    {
      "id": "t32",
      "text": "★ 推奨レベル",
      "x": 5798,
      "y": 72,
      "width": 100,
      "height": 22,
      "fontSize": 11,
      "textColor": "#ffffff",
      "bgColor": "#27ae60",
      "strokeColor": "#27ae60",
      "cornerRadius": 6,
      "textAlign": "center",
      "paddingX": 10,
      "paddingY": 8
    },
    {
      "id": "t33",
      "text": "実装タイムライン\n\nPhase 1 (1-2週間): L1監視ボット\n  → 価格・ポジション監視、アラート通知\n\nPhase 2 (2-4週間): L2半自動\n  → リバランス提案、ワンクリック実行\n\nPhase 3 (1-2ヶ月): L3条件付き全自動\n  → 設定条件内で自動実行、異常時停止\n\nPhase 4 (3ヶ月+): L4完全自動 (将来)\n  → AI判断、パラメータ自動調整",
      "x": 5340,
      "y": 175,
      "width": 440,
      "height": 195,
      "fontSize": 12,
      "textColor": "#2c3e50",
      "bgColor": "#eaf2f8",
      "strokeColor": "#3498db",
      "cornerRadius": 10,
      "textAlign": "left",
      "paddingX": 10,
      "paddingY": 8
    },
    {
      "id": "t34",
      "text": "セキュリティ構成\n\n┌─────────────┐\n│ メインウォレット  │ ← 資金保管\n└──────┬──────┘\n       ↓ 必要額のみ転送\n┌─────────────┐\n│ オペレーション   │ ← Bot操作用\n│ ウォレット      │    上限$5K\n└──────┬──────┘\n       ↓ LP操作のみ\n┌─────────────┐\n│ CLMMポジション  │ ← 流動性提供\n└─────────────┘\n\n・ 秘密鍵は環境変数管理\n・ 出金権限なし(LP操作のみ)\n・ 異常時自動ロック",
      "x": 5820,
      "y": 175,
      "width": 400,
      "height": 310,
      "fontSize": 12,
      "textColor": "#2c3e50",
      "bgColor": "#f5eef8",
      "strokeColor": "#9b59b6",
      "cornerRadius": 10,
      "textAlign": "left",
      "paddingX": 10,
      "paddingY": 8
    },
    {
      "id": "t35",
      "text": "L3が最適: 人間の判断を残しつつ、24/7の市場対応を実現。L4はAI精度が不十分な現段階ではリスク過大",
      "x": 5340,
      "y": 490,
      "width": 880,
      "height": 30,
      "fontSize": 12,
      "textColor": "#f39c12",
      "bgColor": "#fef9e7",
      "strokeColor": "#f1c40f",
      "cornerRadius": 6,
      "textAlign": "center",
      "paddingX": 10,
      "paddingY": 8
    },
    {
      "id": "t36",
      "text": "税務・規制対応（R4 分析）",
      "x": 6400,
      "y": 10,
      "width": 880,
      "height": 40,
      "fontSize": 24,
      "textColor": "#ffffff",
      "bgColor": "#e67e22",
      "strokeColor": "#f39c12",
      "cornerRadius": 12,
      "textAlign": "center",
      "paddingX": 10,
      "paddingY": 8
    },
    {
      "id": "t37",
      "text": "所得区分と税率\n\n個人・雑所得:\n  総合課税 最大55%（所得税45%+住民税10%）\n  損益通算不可、繰越不可\n\n個人・事業所得:\n  青色申告特別控除 65万円\n  経費計上可（VPS、RPC等）\n  損失 3年繰越可\n\n法人:\n  実効税率 約30%\n  損失 10年繰越可\n  役員報酬で所得分散",
      "x": 6400,
      "y": 65,
      "width": 300,
      "height": 235,
      "fontSize": 12,
      "textColor": "#2c3e50",
      "bgColor": "#fef9e7",
      "strokeColor": "#f1c40f",
      "cornerRadius": 10,
      "textAlign": "left",
      "paddingX": 10,
      "paddingY": 8
    },
    {
      "id": "t38",
      "text": "課税イベントフロー\n\nLP開始 (トークン預入):\n  → 時価で「売却」扱い → 課税\n\nLP解除 (トークン引出):\n  → 時価で「取得」扱い → 課税\n\nスワップ実行:\n  → 各スワップが売買 → 課税\n\nリバランス1回 = 3-4課税イベント\n\n⚠ 手動: 60件/年\n⚠ 自動: 400-1,100件/年",
      "x": 6720,
      "y": 65,
      "width": 280,
      "height": 235,
      "fontSize": 12,
      "textColor": "#2c3e50",
      "bgColor": "#fdedec",
      "strokeColor": "#e74c3c",
      "cornerRadius": 10,
      "textAlign": "left",
      "paddingX": 10,
      "paddingY": 8
    },
    {
      "id": "t39",
      "text": "⚠ 重要な警告\n\nCryptact / Koinly:\n  CLMM非対応\n  → 自作CSV変換が必須\n\n必要な対応:\n1. 全TX自動ログ記録\n2. CSV変換スクリプト\n3. 税理士との連携\n4. 四半期ごと仮計算\n\n法人化基準:\n  年利益 > 500万円\n  (税率逆転ポイント)",
      "x": 7020,
      "y": 65,
      "width": 260,
      "height": 235,
      "fontSize": 12,
      "textColor": "#ffffff",
      "bgColor": "#e74c3c",
      "strokeColor": "#c0392b",
      "cornerRadius": 10,
      "textAlign": "left",
      "paddingX": 10,
      "paddingY": 8
    },
    {
      "id": "t40",
      "text": "税務データ管理: Bot内でSQLiteに全TX記録 → 月次CSV出力 → Cryptact手動インポート or 税理士提出用フォーマット",
      "x": 6400,
      "y": 320,
      "width": 880,
      "height": 35,
      "fontSize": 12,
      "textColor": "#2c3e50",
      "bgColor": "#eaf2f8",
      "strokeColor": "#3498db",
      "cornerRadius": 8,
      "textAlign": "center",
      "paddingX": 10,
      "paddingY": 8
    },
    {
      "id": "t41",
      "text": "税引後シミュレーション（$50K運用・基本シナリオ APR16%）\n\n                   | 雑所得(55%)  | 事業所得(45%) | 法人(30%)\n───────────────────────────────────────\n粗利益              | $8,000      | $8,000       | $8,000\n経費控除            | -           | -$637        | -$637\n青色控除            | -           | -$4,200      | -\n課税所得            | $8,000      | $3,163       | $7,363\n税額               | $4,400      | $1,423       | $2,209\n手取り              | $3,600      | $6,577       | $5,791",
      "x": 6400,
      "y": 370,
      "width": 880,
      "height": 150,
      "fontSize": 12,
      "textColor": "#2c3e50",
      "bgColor": "#f8f9fa",
      "strokeColor": "#34495e",
      "cornerRadius": 10,
      "textAlign": "left",
      "paddingX": 10,
      "paddingY": 8
    },
    {
      "id": "t42",
      "text": "インパーマネントロス定量分析（R5）",
      "x": 7460,
      "y": 10,
      "width": 880,
      "height": 40,
      "fontSize": 24,
      "textColor": "#ffffff",
      "bgColor": "#c0392b",
      "strokeColor": "#e74c3c",
      "cornerRadius": 12,
      "textAlign": "center",
      "paddingX": 10,
      "paddingY": 8
    },
    {
      "id": "t43",
      "text": "全損失の77%",
      "x": 7520,
      "y": 155,
      "width": 120,
      "height": 22,
      "fontSize": 11,
      "textColor": "#ffffff",
      "bgColor": "#e74c3c",
      "strokeColor": "#e74c3c",
      "cornerRadius": 4,
      "textAlign": "center",
      "paddingX": 10,
      "paddingY": 8
    },
    {
      "id": "t44",
      "text": "唯一のLP>HODL",
      "x": 7765,
      "y": 155,
      "width": 120,
      "height": 22,
      "fontSize": 11,
      "textColor": "#ffffff",
      "bgColor": "#27ae60",
      "strokeColor": "#27ae60",
      "cornerRadius": 4,
      "textAlign": "center",
      "paddingX": 10,
      "paddingY": 8
    },
    {
      "id": "t45",
      "text": "ILパターン分析\n\nUSDC比率とILの相関:\n  USDC > 70%  → 平均IL -$594\n  USDC 50-70% → 平均IL -$89\n  USDC < 50%  → 平均IL -$24\n\n核心パターン:\n  価格下落 → USDC比率上昇\n  → レンジ外れ → リバランス\n  → 高USDC比率で再投入\n  → さらに下落 → IL爆発\n\nこれが「負のスパイラル」",
      "x": 7970,
      "y": 70,
      "width": 370,
      "height": 210,
      "fontSize": 12,
      "textColor": "#2c3e50",
      "bgColor": "#fdedec",
      "strokeColor": "#e74c3c",
      "cornerRadius": 10,
      "textAlign": "left",
      "paddingX": 10,
      "paddingY": 8
    },
    {
      "id": "t46",
      "text": "改善前（現状）\n\nレンジ外れ率:   90%\n年間IL:        -$3,094\n平均IL/サイクル: -$309\nリバランス頻度:  高頻度\n手数料回収:     ILで相殺\nネット収益:     マイナス",
      "x": 7460,
      "y": 290,
      "width": 280,
      "height": 170,
      "fontSize": 13,
      "textColor": "#ffffff",
      "bgColor": "#e74c3c",
      "strokeColor": "#c0392b",
      "cornerRadius": 10,
      "textAlign": "left",
      "paddingX": 10,
      "paddingY": 8
    },
    {
      "id": "t47",
      "text": "改善後（2σ戦略）\n\nレンジ外れ率:   20%以下\n年間IL:        -$800以下\n平均IL/サイクル: -$67\nリバランス頻度:  月4-8回\n手数料回収:     ILを上回る\nネット収益:     プラス転換",
      "x": 7760,
      "y": 290,
      "width": 280,
      "height": 170,
      "fontSize": 13,
      "textColor": "#ffffff",
      "bgColor": "#27ae60",
      "strokeColor": "#1e8449",
      "cornerRadius": 10,
      "textAlign": "left",
      "paddingX": 10,
      "paddingY": 8
    },
    {
      "id": "t48",
      "text": "IL削減の鍵\n\n1. レンジ幅拡大で外れ率↓\n2. クールダウンで無駄TX↓\n3. 3層構造で常時稼働確保\n4. USDC偏重検知で自動停止\n5. トレンドバイアスで方向性対応",
      "x": 8060,
      "y": 290,
      "width": 280,
      "height": 170,
      "fontSize": 13,
      "textColor": "#2c3e50",
      "bgColor": "#f5eef8",
      "strokeColor": "#9b59b6",
      "cornerRadius": 10,
      "textAlign": "left",
      "paddingX": 10,
      "paddingY": 8
    },
    {
      "id": "t49",
      "text": "試算: IL -$3,094→-$800 = $2,294の改善。$50K運用で+4.6%のAPR改善に相当",
      "x": 7460,
      "y": 480,
      "width": 880,
      "height": 35,
      "fontSize": 13,
      "textColor": "#27ae60",
      "bgColor": "#eafaf1",
      "strokeColor": "#27ae60",
      "cornerRadius": 8,
      "textAlign": "center",
      "paddingX": 10,
      "paddingY": 8
    },
    {
      "id": "t50",
      "text": "インフラ構成（R6 技術基盤）",
      "x": 8520,
      "y": 10,
      "width": 880,
      "height": 40,
      "fontSize": 24,
      "textColor": "#ffffff",
      "bgColor": "#2c3e50",
      "strokeColor": "#34495e",
      "cornerRadius": 12,
      "textAlign": "center",
      "paddingX": 10,
      "paddingY": 8
    },
    {
      "id": "t51",
      "text": "月間コスト内訳\n\nVPS (Hetzner CPX11):   €4.15 (~$4.60)\nRPC (Helius Business): $49.00\nドメイン/SSL:          $0.50\n監視 (UptimeRobot):    $0.00\nアラート (Discord):    $0.00\n────────────────────\n月間合計:              $53.10\n年間合計:              $637.20",
      "x": 8520,
      "y": 250,
      "width": 340,
      "height": 180,
      "fontSize": 12,
      "textColor": "#2c3e50",
      "bgColor": "#eaf2f8",
      "strokeColor": "#3498db",
      "cornerRadius": 10,
      "textAlign": "left",
      "paddingX": 10,
      "paddingY": 8
    },
    {
      "id": "t52",
      "text": "可用性・監視\n\n目標稼働率: 99.5%（月間ダウン3.6h以下）\n\n監視項目:\n  ・ プロセス死活 (毎10秒)\n  ・ RPC応答速度 (毎30秒)\n  ・ ポジション状態 (毎30秒)\n  ・ ウォレット残高 (毎5分)\n  ・ ディスク/メモリ (毎1分)\n\nアラート先:\n  Discord Webhook → 即時通知\n  LINE Notify → 緊急時バックアップ",
      "x": 8890,
      "y": 250,
      "width": 290,
      "height": 215,
      "fontSize": 12,
      "textColor": "#2c3e50",
      "bgColor": "#fef9e7",
      "strokeColor": "#f1c40f",
      "cornerRadius": 10,
      "textAlign": "left",
      "paddingX": 10,
      "paddingY": 8
    },
    {
      "id": "t53",
      "text": "障害対応\n\nRPC障害:\n  → 自動フォールバック\n  → 3系統で冗長化\n\nBot停止:\n  → Docker自動再起動\n  → systemd watchdog\n\nVPS障害:\n  → スナップショット復元\n  → 復旧目標: 30分以内",
      "x": 9200,
      "y": 250,
      "width": 200,
      "height": 215,
      "fontSize": 12,
      "textColor": "#ffffff",
      "bgColor": "#e74c3c",
      "strokeColor": "#c0392b",
      "cornerRadius": 10,
      "textAlign": "left",
      "paddingX": 10,
      "paddingY": 8
    },
    {
      "id": "t54",
      "text": "年間インフラコスト$637は運用額$50Kの1.3%。APR改善幅(+3～28%)に対して十分小さい",
      "x": 8520,
      "y": 490,
      "width": 880,
      "height": 30,
      "fontSize": 12,
      "textColor": "#27ae60",
      "bgColor": "#eafaf1",
      "strokeColor": "#27ae60",
      "cornerRadius": 6,
      "textAlign": "center",
      "paddingX": 10,
      "paddingY": 8
    },
    {
      "id": "t55",
      "text": "資金配分戦略（R7+R8）",
      "x": 9580,
      "y": 10,
      "width": 880,
      "height": 40,
      "fontSize": 24,
      "textColor": "#ffffff",
      "bgColor": "#1e8449",
      "strokeColor": "#27ae60",
      "cornerRadius": 12,
      "textAlign": "center",
      "paddingX": 10,
      "paddingY": 8
    },
    {
      "id": "t56",
      "text": "ハイブリッド運用アプローチ\n\nKamino Vault: $30K（短期・即時開始）\n  → 自動リバランス済、APR 8-15%\n  → 手間なし、学習期間に最適\n\n自作Bot: $10K（中期・開発後）\n  → 2σ戦略で高APR狙い\n  → 段階的に資金移行\n\nCetus (SUI): $10K（分散用）\n  → SUIエコシステム分散\n  → Botから管理",
      "x": 9580,
      "y": 195,
      "width": 430,
      "height": 190,
      "fontSize": 13,
      "textColor": "#2c3e50",
      "bgColor": "#eaf2f8",
      "strokeColor": "#3498db",
      "cornerRadius": 10,
      "textAlign": "left",
      "paddingX": 10,
      "paddingY": 8
    },
    {
      "id": "t57",
      "text": "⚠ SUI/Cetusリスク警告\n\nTVL: ピーク比 -78%\nCETUSトークン: -90%下落\n2025年4月: 大量アンロック予定\n\n対策:\n  → SUI配分を15%に制限\n  → 利益は週次でUSDC変換\n  → TVL監視、閾値割れで撤退\n  → アンロック前にポジション縮小",
      "x": 10040,
      "y": 195,
      "width": 420,
      "height": 190,
      "fontSize": 13,
      "textColor": "#ffffff",
      "bgColor": "#e74c3c",
      "strokeColor": "#c0392b",
      "cornerRadius": 10,
      "textAlign": "left",
      "paddingX": 10,
      "paddingY": 8
    },
    {
      "id": "t58",
      "text": "SOL/mSOLの利点: 相関ペアでILが極めて小さい (年間<0.5%) + ステーキング報酬。安定収益の土台として10%配分。",
      "x": 9580,
      "y": 410,
      "width": 440,
      "height": 55,
      "fontSize": 12,
      "textColor": "#2c3e50",
      "bgColor": "#eafaf1",
      "strokeColor": "#27ae60",
      "cornerRadius": 8,
      "textAlign": "left",
      "paddingX": 10,
      "paddingY": 8
    },
    {
      "id": "t59",
      "text": "予備資金の役割: 急落時の買い増し、ガス代、緊急リバランス用。最低$5Kを常時確保。予備不足は機会損失に直結。",
      "x": 10040,
      "y": 410,
      "width": 420,
      "height": 55,
      "fontSize": 12,
      "textColor": "#2c3e50",
      "bgColor": "#fef9e7",
      "strokeColor": "#f1c40f",
      "cornerRadius": 8,
      "textAlign": "left",
      "paddingX": 10,
      "paddingY": 8
    },
    {
      "id": "t60",
      "text": "原則: Kamino(安定)で収益確保しつつ、自作Bot(高収益)を段階開発。失敗しても全体の20%リスクに限定。",
      "x": 9580,
      "y": 490,
      "width": 880,
      "height": 30,
      "fontSize": 12,
      "textColor": "#2c3e50",
      "bgColor": "#f8f9fa",
      "strokeColor": "#34495e",
      "cornerRadius": 6,
      "textAlign": "center",
      "paddingX": 10,
      "paddingY": 8
    },
    {
      "id": "t61",
      "text": "バックテスト結果（R9 検証）",
      "x": 10640,
      "y": 10,
      "width": 880,
      "height": 40,
      "fontSize": 24,
      "textColor": "#ffffff",
      "bgColor": "#1e8449",
      "strokeColor": "#27ae60",
      "cornerRadius": 12,
      "textAlign": "center",
      "paddingX": 10,
      "paddingY": 8
    },
    {
      "id": "t62",
      "text": "戦略ランキング詳細\n\n順位 | 戦略          | ネットAPR | IL    | シャープ比\n──────────────────────────────────────────\n#1  | D: ボラ連動2σ  | +16.2%  | -1.6% | 1.42\n#2  | B: 広レンジ±15%| +12.8%  | -1.1% | 1.21\n#3  | F: トレンド追従  | +14.5%  | -2.8% | 1.15\n#4  | E: 時間加重     | +11.3%  | -1.9% | 1.08\n#5  | C: ボリンジャー  | +10.1%  | -2.3% | 0.95\n#6  | A: 狭レンジ±5% | +2.1%   | -6.2% | 0.31",
      "x": 10640,
      "y": 170,
      "width": 560,
      "height": 155,
      "fontSize": 12,
      "textColor": "#2c3e50",
      "bgColor": "#eafaf1",
      "strokeColor": "#27ae60",
      "cornerRadius": 10,
      "textAlign": "left",
      "paddingX": 10,
      "paddingY": 8
    },
    {
      "id": "t63",
      "text": "核心的発見\n\n現状の戦略A(狭レンジ)は\nほぼ最下位。\n\nAPR差: +2.1% vs +16.2%\n= 年間$7,050の機会損失\n\n戦略Dへの移行が\n最優先アクション。",
      "x": 11220,
      "y": 170,
      "width": 300,
      "height": 155,
      "fontSize": 13,
      "textColor": "#ffffff",
      "bgColor": "#e74c3c",
      "strokeColor": "#c0392b",
      "cornerRadius": 10,
      "textAlign": "left",
      "paddingX": 10,
      "paddingY": 8
    },
    {
      "id": "t64",
      "text": "モンテカルロ分析（1000パス）\n\n戦略D（ボラ連動）の結果:\n  中央値APR:     +15.8%\n  5パーセンタイル: +6.2%（最悪ケース）\n  95パーセンタイル:+24.1%（最良ケース）\n  最大ドローダウン: -8.3%\n  破産確率: 0.1%以下\n\nリスク調整後リターンで全戦略中最良",
      "x": 10640,
      "y": 350,
      "width": 430,
      "height": 160,
      "fontSize": 12,
      "textColor": "#2c3e50",
      "bgColor": "#f5eef8",
      "strokeColor": "#9b59b6",
      "cornerRadius": 10,
      "textAlign": "left",
      "paddingX": 10,
      "paddingY": 8
    },
    {
      "id": "t65",
      "text": "パラメータ・ロバスト性\n\n戦略Dはパラメータ変動に最も強い:\n  σ倍率 1.5-2.5 → APR 12-18%\n  ATR期間 10-20 → APR 14-17%\n  クールダウン 2-8h → APR 13-17%\n\n戦略Aはパラメータ敏感:\n  レンジ幅 ±3-7% → APR -2%～+5%\n  → 最適値が狭く実運用で不安定",
      "x": 11100,
      "y": 350,
      "width": 420,
      "height": 160,
      "fontSize": 12,
      "textColor": "#2c3e50",
      "bgColor": "#fef9e7",
      "strokeColor": "#f1c40f",
      "cornerRadius": 10,
      "textAlign": "left",
      "paddingX": 10,
      "paddingY": 8
    },
    {
      "id": "t66",
      "text": "実装ロードマップ（R10）",
      "x": 11700,
      "y": 10,
      "width": 880,
      "height": 40,
      "fontSize": 24,
      "textColor": "#ffffff",
      "bgColor": "#2980b9",
      "strokeColor": "#3498db",
      "cornerRadius": 12,
      "textAlign": "center",
      "paddingX": 10,
      "paddingY": 8
    },
    {
      "id": "t67",
      "text": "即時アクション\n\n1. 現行レンジを±12%に拡大\n2. リバランス頻度を制限\n3. Kamino Vaultに$30K移行\n4. バックテスト環境構築\n5. VPS(Hetzner)契約",
      "x": 11690,
      "y": 160,
      "width": 210,
      "height": 150,
      "fontSize": 11,
      "textColor": "#2c3e50",
      "bgColor": "#fdedec",
      "strokeColor": "#e74c3c",
      "cornerRadius": 8,
      "textAlign": "left",
      "paddingX": 10,
      "paddingY": 8
    },
    {
      "id": "t68",
      "text": "1ヶ月目標\n\n1. 監視Bot (L1) 稼働\n2. 2σパラメータ確定\n3. SQLiteログ構築\n4. Discord通知連携\n5. 税務CSV出力機能",
      "x": 11920,
      "y": 160,
      "width": 200,
      "height": 150,
      "fontSize": 11,
      "textColor": "#2c3e50",
      "bgColor": "#fef9e7",
      "strokeColor": "#f39c12",
      "cornerRadius": 8,
      "textAlign": "left",
      "paddingX": 10,
      "paddingY": 8
    },
    {
      "id": "t69",
      "text": "1-3ヶ月目標\n\n1. L2半自動Bot稼働\n2. 自作Botに$10K投入\n3. 3層ポジション実装\n4. バックテスト継続検証\n5. SUI/Cetus Bot連携",
      "x": 12140,
      "y": 160,
      "width": 200,
      "height": 150,
      "fontSize": 11,
      "textColor": "#2c3e50",
      "bgColor": "#eaf2f8",
      "strokeColor": "#3498db",
      "cornerRadius": 8,
      "textAlign": "left",
      "paddingX": 10,
      "paddingY": 8
    },
    {
      "id": "t70",
      "text": "3-6ヶ月目標\n\n1. L3条件付き全自動\n2. Kamino→自作Bot移行\n3. パラメータ自動調整\n4. 税務レポート自動化\n5. 法人化検討",
      "x": 12360,
      "y": 160,
      "width": 210,
      "height": 150,
      "fontSize": 11,
      "textColor": "#2c3e50",
      "bgColor": "#eafaf1",
      "strokeColor": "#27ae60",
      "cornerRadius": 8,
      "textAlign": "left",
      "paddingX": 10,
      "paddingY": 8
    },
    {
      "id": "t71",
      "text": "技術スタック\n\nPython:     バックテスト・分析・ML\nTypeScript: Bot本体・Solana/Sui SDK\nDocker:     コンテナ化・環境統一\nSQLite:     TX記録・パフォーマンス追跡\nHetzner:    VPS (CPX11 2vCPU/4GB)\nHelius:     Solana RPC ($49/月)",
      "x": 11700,
      "y": 335,
      "width": 300,
      "height": 150,
      "fontSize": 12,
      "textColor": "#2c3e50",
      "bgColor": "#f8f9fa",
      "strokeColor": "#34495e",
      "cornerRadius": 10,
      "textAlign": "left",
      "paddingX": 10,
      "paddingY": 8
    },
    {
      "id": "t72",
      "text": "成功KPI\n\nレンジ内稼働率:  70%以上 (現状10%)\nネットAPR:      15%以上 (現状2%)\nリバランス頻度:  4-8回/月 (現状30+回)\nIL/サイクル:    -$100以下 (現状-$309)\nBot稼働率:      99.5%以上\n月間コスト:      $55以下",
      "x": 12030,
      "y": 335,
      "width": 280,
      "height": 150,
      "fontSize": 12,
      "textColor": "#ffffff",
      "bgColor": "#27ae60",
      "strokeColor": "#1e8449",
      "cornerRadius": 10,
      "textAlign": "left",
      "paddingX": 10,
      "paddingY": 8
    },
    {
      "id": "t73",
      "text": "リスク管理\n\n最大損失限度: $5K (10%)\n  → 超過時Bot自動停止\n日次損失限度: $500\n  → 超過時アラート+停止\n緊急連絡: Discord即時\n週次レビュー: 必須\n月次パラメータ調整",
      "x": 12340,
      "y": 335,
      "width": 240,
      "height": 150,
      "fontSize": 12,
      "textColor": "#2c3e50",
      "bgColor": "#fdedec",
      "strokeColor": "#e74c3c",
      "cornerRadius": 10,
      "textAlign": "left",
      "paddingX": 10,
      "paddingY": 8
    },
    {
      "id": "t74",
      "text": "収益シミュレーション（R10 総合試算）",
      "x": 12760,
      "y": 10,
      "width": 880,
      "height": 40,
      "fontSize": 24,
      "textColor": "#ffffff",
      "bgColor": "#1e8449",
      "strokeColor": "#27ae60",
      "cornerRadius": 12,
      "textAlign": "center",
      "paddingX": 10,
      "paddingY": 8
    },
    {
      "id": "t75",
      "text": "保守的シナリオ\n\n手数料収入:  $3,500\nIL:           -$1,500\nインフラ:   -$637\nガス/TX:    -$200\n─────────────────\n粗利益:     $1,163\n税(55%):    -$640\n─────────────────\n手取り:     $523\nAPR(税後):  +1.0%",
      "x": 12750,
      "y": 155,
      "width": 210,
      "height": 210,
      "fontSize": 12,
      "textColor": "#2c3e50",
      "bgColor": "#fdedec",
      "strokeColor": "#e74c3c",
      "cornerRadius": 10,
      "textAlign": "left",
      "paddingX": 10,
      "paddingY": 8
    },
    {
      "id": "t76",
      "text": "基本シナリオ ★推奨\n\n手数料収入:  $10,000\nIL:           -$800\nインフラ:   -$637\nガス/TX:    -$300\n──────────────────\n粗利益:     $8,263\n税(55%):    -$4,545\n──────────────────\n手取り:     $3,718\nAPR(税後):  +7.4%",
      "x": 12990,
      "y": 155,
      "width": 210,
      "height": 210,
      "fontSize": 12,
      "textColor": "#2c3e50",
      "bgColor": "#eaf2f8",
      "strokeColor": "#3498db",
      "cornerRadius": 10,
      "textAlign": "left",
      "paddingX": 10,
      "paddingY": 8
    },
    {
      "id": "t77",
      "text": "楽観的シナリオ\n\n手数料収入:  $17,000\nIL:           -$500\nインフラ:   -$637\nガス/TX:    -$400\n──────────────────\n粗利益:     $15,463\n税(55%):    -$8,505\n──────────────────\n手取り:     $6,958\nAPR(税後):  +13.9%",
      "x": 13230,
      "y": 155,
      "width": 210,
      "height": 210,
      "fontSize": 12,
      "textColor": "#2c3e50",
      "bgColor": "#eafaf1",
      "strokeColor": "#27ae60",
      "cornerRadius": 10,
      "textAlign": "left",
      "paddingX": 10,
      "paddingY": 8
    },
    {
      "id": "t78",
      "text": "HODLとの比較\n\n$50K HODL(SOL)の場合:\n  上昇時: LP < HODL\n  横這い: LP >> HODL\n  下落時: LP > HODL\n\nCLMM LPの本質:\n  ボラを手数料に変換\n  方向性ベットではなく\n  ボラティリティ収穫",
      "x": 13470,
      "y": 155,
      "width": 180,
      "height": 210,
      "fontSize": 11,
      "textColor": "#2c3e50",
      "bgColor": "#f5eef8",
      "strokeColor": "#9b59b6",
      "cornerRadius": 8,
      "textAlign": "left",
      "paddingX": 10,
      "paddingY": 8
    },
    {
      "id": "t79",
      "text": "年間コスト総額\n\n保守的: $1,637 (インフラ$637 + TX$200 + 税$640 + 予備$160) = 運用額の3.3%\n基本:   $5,482 (インフラ$637 + TX$300 + 税$4,545) → 税は利益から\n楽観的: $9,542 (インフラ$637 + TX$400 + 税$8,505) → 高税額だが高利益",
      "x": 12760,
      "y": 390,
      "width": 880,
      "height": 75,
      "fontSize": 12,
      "textColor": "#2c3e50",
      "bgColor": "#fef9e7",
      "strokeColor": "#f1c40f",
      "cornerRadius": 10,
      "textAlign": "left",
      "paddingX": 10,
      "paddingY": 8
    },
    {
      "id": "t80",
      "text": "結論: 基本シナリオで税引後APR 7.4%。事業所得化で12.4%に改善可能。戦略Dへの移行が最重要アクション。",
      "x": 12760,
      "y": 485,
      "width": 880,
      "height": 35,
      "fontSize": 14,
      "textColor": "#ffffff",
      "bgColor": "#27ae60",
      "strokeColor": "#1e8449",
      "cornerRadius": 8,
      "textAlign": "center",
      "paddingX": 10,
      "paddingY": 8
    }
  ],
  "groups": [],
  "printPages": [
    {
      "id": "page1",
      "label": "タイトル & エグゼクティブサマリー",
      "x": 0,
      "y": 0,
      "width": 960,
      "height": 540,
      "orientation": "landscape",
      "preset": "slide"
    },
    {
      "id": "page2",
      "label": "現状の問題分析（R1+R5）",
      "x": 1060,
      "y": 0,
      "width": 960,
      "height": 540,
      "orientation": "landscape",
      "preset": "slide"
    },
    {
      "id": "page3",
      "label": "レンジ戦略比較（R2）",
      "x": 2120,
      "y": 0,
      "width": 960,
      "height": 540,
      "orientation": "landscape",
      "preset": "slide"
    },
    {
      "id": "page4",
      "label": "ボラ連動2σ戦略詳細（R2+R9）",
      "x": 3180,
      "y": 0,
      "width": 960,
      "height": 540,
      "orientation": "landscape",
      "preset": "slide"
    },
    {
      "id": "page5",
      "label": "リバランスロジック（R2+R3）",
      "x": 4240,
      "y": 0,
      "width": 960,
      "height": 540,
      "orientation": "landscape",
      "preset": "slide"
    },
    {
      "id": "page6",
      "label": "自動化レベル（R3）",
      "x": 5300,
      "y": 0,
      "width": 960,
      "height": 540,
      "orientation": "landscape",
      "preset": "slide"
    },
    {
      "id": "page7",
      "label": "税務・規制（R4）",
      "x": 6360,
      "y": 0,
      "width": 960,
      "height": 540,
      "orientation": "landscape",
      "preset": "slide"
    },
    {
      "id": "page8",
      "label": "IL定量分析（R5）",
      "x": 7420,
      "y": 0,
      "width": 960,
      "height": 540,
      "orientation": "landscape",
      "preset": "slide"
    },
    {
      "id": "page9",
      "label": "インフラ構成（R6）",
      "x": 8480,
      "y": 0,
      "width": 960,
      "height": 540,
      "orientation": "landscape",
      "preset": "slide"
    },
    {
      "id": "page10",
      "label": "資金配分（R7+R8）",
      "x": 9540,
      "y": 0,
      "width": 960,
      "height": 540,
      "orientation": "landscape",
      "preset": "slide"
    },
    {
      "id": "page11",
      "label": "バックテスト結果（R9）",
      "x": 10600,
      "y": 0,
      "width": 960,
      "height": 540,
      "orientation": "landscape",
      "preset": "slide"
    },
    {
      "id": "page12",
      "label": "実装ロードマップ（R10）",
      "x": 11660,
      "y": 0,
      "width": 960,
      "height": 540,
      "orientation": "landscape",
      "preset": "slide"
    },
    {
      "id": "page13",
      "label": "収益シミュレーション（R10）",
      "x": 12720,
      "y": 0,
      "width": 960,
      "height": 540,
      "orientation": "landscape",
      "preset": "slide"
    }
  ],
  "layoutMode": "layout",
  "framePreset": "slide"
}